command/__init__.py
command/command.py
command/group.py
tests/__init__.py
tests/conftest.py
tests/test_cli.py
cmd_tools-0.0.11.dist-info/METADATA
cmd_tools-0.0.11.dist-info/WHEEL
cmd_tools-0.0.11.dist-info/entry_points.txt
cmd_tools-0.0.11.dist-info/top_level.txt
cmd_tools-0.0.11.dist-info/RECORD
