Metadata-Version: 2.1
Name: cmd-tools
Version: 0.0.11
Summary: command tools
Home-page: UNKNOWN
Author: buglan
Author-email: 1831353087@qq.com
License: UNKNOWN
Platform: UNKNOWN
Requires-Dist: click
